<?xml version="1.0" encoding="Windows-1252"?>
<string_table>

	<string id="ui_inv_outfit_speed">
		<text>Velocidad</text>
	</string><!-- MCM --><string id="ui_mcm_menu_speed">
		<text>Velocidad</text>
	</string>
	<string id="ui_mcm_menu_speed_title">
		<text>Trajes/armas afectan a la velocidad de movimiento</text>
	</string>
	<string id="ui_mcm_speed_title">
		<text>Trajes/armas afectan a la velocidad de movimiento</text>
	</string>
	<string id="ui_mcm_speed_encumbrance">
		<text>Carga afecta a la velocidad</text>
	</string>
	<string id="ui_mcm_speed_encumbrance_desc">
		<text>La carga conlleva bonificaciones cuando es una carga ligera (menos del 25 % de la carga total) y penalizaciones cuando es una carga pesada (más del 70 %).\n \nTen en cuenta que, si activas esta opción, viajarás a una velocidad escandalosa con poco peso.</text>
	</string>
	<string id="ui_mcm_speed_weapon">
		<text>Arma afecta a la velocidad de esprint</text>
	</string>
	<string id="ui_mcm_speed_weapon_desc">
		<text>Si se activa, las armas aplican un modificador a la velocidad de esprint dependiendo de su peso y tipo.</text>
	</string>
	<string id="ui_mcm_speed_debug">
		<text>(Desarrollo) Registros adicionales en consola</text>
	</string>
	<string id="ui_mcm_speed_debug_desc">
		<text>Imprime chorradas útiles en la consola.</text>
	</string>
</string_table>
