<?xml version="1.0" encoding="Windows-1252"?>
<string_table>

	<string id="name_isg_private_0">
		<text>Soldado</text>
	</string>
	<string id="name_isg_private_1">
		<text>Soldado primero</text>
	</string>
	<string id="name_isg_private_2">
		<text>Cabo</text>
	</string>
	<string id="name_isg_sergeant_0">
		<text>Sargento</text>
	</string>
	<string id="name_isg_sergeant_1">
		<text>Sargento mayor</text>
	</string>
	<string id="name_isg_sergeant_2">
		<text>Suboficial mayor</text>
	</string>
	<string id="name_isg_lieutenant_0">
		<text>Subteniente</text>
	</string>
	<string id="name_isg_lieutenant_1">
		<text>Teniente</text>
	</string>
	<string id="name_isg_captain_0">
		<text>Capitán</text>
	</string>

</string_table>
